<?xml version="1.0" encoding="UTF-8" standalone="no"?>
<databaseChangeLog xmlns="http://www.liquibase.org/xml/ns/dbchangelog"
	xmlns:xsi="http://www.w3.org/2001/XMLSchema-instance"
	xsi:schemaLocation="http://www.liquibase.org/xml/ns/dbchangelog
         http://www.liquibase.org/xml/ns/dbchangelog/dbchangelog-3.1.xsd">
 

<changeSet author="emtudorsm" id="8">
<createTable tableName="person_t" remarks="Holds information about a (contact) person (for a end-point).">
  <column name="person_id" type="INTEGER">
    <constraints nullable="false"/>
  </column>
  <column name="first_name" type="VARCHAR(32)" remarks="The first or given name of the person"/>
  <column name="last_name" type="VARCHAR(32)" remarks="The last or family name of the person"/>
  <column name="phone_number" type="VARCHAR(32)" remarks="The person phone number"/>
  <column name="mobile_number" type="VARCHAR(32)" remarks="The person mobile phone number"/>
  <column name="fax_number" type="VARCHAR(32)" remarks="The person fax number"/>
  <column name="e_mail" type="VARCHAR(64)" remarks="The person e-mail address"/>
  <column name="created_by" type="VARCHAR(32)" remarks="The name of the user who created the entry">
    <constraints nullable="false"/>
  </column>
  <column name="created_on" type="TIMESTAMP" remarks="The date and time the entry was created">
    <constraints nullable="false"/>
  </column>
  <column name="modified_by" type="VARCHAR(32)" remarks="The name of the user who performed the last update on the entry"/>
  <column name="modified_on" type="TIMESTAMP" remarks="The date and time the entry was last updated"/>
</createTable>
<rollback> <dropTable tableName="person_t" cascadeConstraints="true"/></rollback>
</changeSet>
<changeSet author="emtudorsm" id="9">
<addPrimaryKey tableName="person_t" constraintName="pk_person" columnNames="person_id"/>
</changeSet>
	    	
<changeSet author="emtudorsm" id="81">
 <createSequence sequenceName="sq_person" startValue="100000" incrementBy="1" minValue="1"/>
 <rollback>
		<dropSequence sequenceName="sq_person"/>
	</rollback>
</changeSet>        	        
 </databaseChangeLog>